{
  "parent": "minecraft:recipes/root",
  "rewards": {
	"recipes": [
	  "techreborn:industrial_grinder/venus_rock_with_water"
	]
  },
  "criteria": {
	"has_venus_rock": {
	  "trigger": "minecraft:inventory_changed",
	  "conditions": {
		"items": [
		  {
			"tag": "c:venus_rocks"
		  }
		]
	  }
	},
	"has_the_recipe": {
	  "trigger": "minecraft:recipe_unlocked",
	  "conditions": {
		"recipe": "techreborn:industrial_grinder/venus_rock_with_water"
	  }
	}
  },
  "requirements": [
	[
	  "has_venus_rock",
	  "has_the_recipe"
	]
  ]
}